{
  "name": "Sapphillon CLI Development",
  "image": "mcr.microsoft.com/devcontainers/base:ubuntu",
  "features": {
    "ghcr.io/devcontainers/features/common-utils:2": {},
    "ghcr.io/devcontainers-contrib/features/deno:1": {}
  },
  "customizations": {
    "vscode": {
      "extensions": [
        "denoland.vscode-deno"
      ],
      "settings": {
        "deno.enable": true,
        "deno.lint": true,
        "deno.unstable": false,
        "editor.formatOnSave": true,
        "editor.defaultFormatter": "denoland.vscode-deno",
        "[typescript]": {
          "editor.defaultFormatter": "denoland.vscode-deno"
        }
      }
    }
  },
  "postCreateCommand": "deno --version && make help"
}
